{
	"market": {
		"approvedValue": "",
		"changed": false,
		"changeNotes": "",
		"suggestion": "Marine Stadium",
		"details": ["This report was prepared specifically for this market."]
	},
	"employee": {
		"approvedValue": "",
		"changed": false,
		"changeNotes": "",
		"suggestion": "CJ Adams",
		"details": ["CJ was scheduled to work this market."]
	},
	"date": {
		"approvedValue": "",
		"changed": false,
		"changeNotes": "",
		"suggestion": "7/27/16",
		"details": ["This report was generated on 7/27/16 for this market on 7/27/16."]
	},
	"sales": {
		"approvedValue": "",
		"changed": false,
		"changeNotes": "",
		"suggestion": "$173.00",
		"details": [
			"Gross Sales: $173.00",
			"Total Discounts: -$8.00",
			"Total Refunds: -$0.00",
			"Net Sales: $165.00"
		]
	},
	"till": {
		"approvedValue": "",
		"changed": false,
		"changeNotes": "",
		"suggestion": "$225.00",
		"details": [
			"Based on your sales, this is how much cash should be left in your drawer.",
			"This number includes your starting bank of $60.00."
		]
	},
	"rent": {
		"approvedValue": "",
		"changed": false,
		"changeNotes": "",
		"suggestion": "$20.00",
		"details": [
		"Gross Sales: $173.00",
		"Market Percentage: 20%",
		"Percentage Fee: $18.00",
		"Flat Fee: $2.00",
		"Total Market Rent: $20.00"
		]
	},
	"pay": {
		"approvedValue": "",
		"changed": false,
		"changeNotes": "",
		"suggestion": "$50.00", 
		"details": [
			"Total Market Hours (3:00 PM - 8:00 PM): 5 hrs",
			"Hourly Guaranteed Rate: $10/hr",
			"Hourly Guaranteed Subtotal: $50.00",
			"Commission Rate: 20%",
			"Commission Subtotal: $35.00",
			"Hourly ($50.00) > Commission ($35.00)",
			"Pay From Guarantee: $50.00",
			"Pay From Commission: $0.00",
			"Total Pay: $50.00"
		]
	},
	"bank": {
		"approvedValue": "",
		"changed": false,
		"changeNotes": "",
		"suggestion": "$60.00",
		"details": [
			"You should have started the market with $60.00 of bank."
		]
	},
	"due": {
		"approvedValue": "",
		"changed": false,
		"changeNotes": "",
		"suggestion": "$95.00",
		"details": [
			"Final Till Cash: $225.00",
			"Market Fee: -$20.00",
			"Employee Pay: -$50.00",
			"Starting Bank: -$60.00",
			"Total Due To Ah-Nuts: $95.00"
		]
	}
}